setup.py
pycryptoguard/__init__.py
pycryptoguard/encrypt_decrypt.py
pycryptoguard.egg-info/PKG-INFO
pycryptoguard.egg-info/SOURCES.txt
pycryptoguard.egg-info/dependency_links.txt
pycryptoguard.egg-info/requires.txt
pycryptoguard.egg-info/top_level.txt