Metadata-Version: 2.1
Name: pycryptoguard
Version: 0.3.15
Summary: A library for encrypting files with AES
Author: INeddHelp
Author-email: ineddhelpgithub@gmail.com
